[{"_id":"5fc79f1c8a477f80c0cf4397","conversationid":"5fc78bb694632358e5f3891e_tufike_5f628a855c2771d2cf3d7bf6","sender":"5fc78bb694632358e5f3891e","receiver":"5f628a855c2771d2cf3d7bf6","sendername":"Nicole Moraa","receivername":"Felix Oenga","senderphoto":"5fc78bb694632358e5f3891e.png","receiverphoto":"5f628a855c2771d2cf3d7bf6.png","message":"Hello there Mr Felix. How are you doing?","status":1,"time":1606917916640,"createdAt":"2020-12-02T14:05:16.675Z","updatedAt":"2020-12-28T18:43:34.935Z","__v":0},{"_id":"5fc79f7d8a477f80c0cf4398","conversationid":"5fc78bb694632358e5f3891e_tufike_5f628a855c2771d2cf3d7bf6","sender":"5f628a855c2771d2cf3d7bf6","receiver":"5fc78bb694632358e5f3891e","sendername":"Felix Oenga","receivername":"Nicole Moraa","senderphoto":"5f628a855c2771d2cf3d7bf6.png","receiverphoto":"5fc78bb694632358e5f3891e.png","message":"I'm fine sir. Thank you for asking. How are you doing?","status":1,"time":1606918013764,"createdAt":"2020-12-02T14:06:53.778Z","updatedAt":"2020-12-28T18:43:34.935Z","__v":0},{"_id":"5fc835ad4f63ce34c3194f39","conversationid":"5fc78bb694632358e5f3891e_tufike_5f628a855c2771d2cf3d7bf6","sender":"5fc78bb694632358e5f3891e","receiver":"5f628a855c2771d2cf3d7bf6","sendername":"Nicole Moraa","receivername":"Felix Oenga","senderphoto":"5fc78bb694632358e5f3891e.png","receiverphoto":"5f628a855c2771d2cf3d7bf6.png","message":"Great is for thou","status":1,"time":1606956461456,"createdAt":"2020-12-03T00:47:41.478Z","updatedAt":"2020-12-28T18:43:34.935Z","__v":0},{"_id":"5fc8d03e3713801160b946fb","conversationid":"5fc78bb694632358e5f3891e_tufike_5f628a855c2771d2cf3d7bf6","sender":"5f628a855c2771d2cf3d7bf6","receiver":"5fc78bb694632358e5f3891e","sendername":"Felix Oenga","receivername":"Nicole Moraa","senderphoto":"5f628a855c2771d2cf3d7bf6.png","receiverphoto":"5fc78bb694632358e5f3891e.png","message":"Likewise to you too","status":1,"time":1606996030849,"createdAt":"2020-12-03T11:47:10.860Z","updatedAt":"2020-12-28T18:43:34.935Z","__v":0},{"_id":"5fcba1d27d1d61c03a6306ac","conversationid":"5fc78bb694632358e5f3891e_tufike_5f628a855c2771d2cf3d7bf6","sender":"5fc78bb694632358e5f3891e","receiver":"5f628a855c2771d2cf3d7bf6","sendername":"Nicole Moraa","receivername":"Felix Oenga","senderphoto":"5fc78bb694632358e5f3891e.png","receiverphoto":"5f628a855c2771d2cf3d7bf6.png","message":"Hey there, how are you doing?","status":1,"time":1607180754315,"createdAt":"2020-12-05T15:05:54.355Z","updatedAt":"2020-12-28T18:43:34.935Z","__v":0},{"_id":"5fcba1f27d1d61c03a6306ad","conversationid":"5fc78bb694632358e5f3891e_tufike_5f628a855c2771d2cf3d7bf6","sender":"5f628a855c2771d2cf3d7bf6","receiver":"5fc78bb694632358e5f3891e","sendername":"Felix Oenga","receivername":"Nicole Moraa","senderphoto":"5f628a855c2771d2cf3d7bf6.png","receiverphoto":"5fc78bb694632358e5f3891e.png","message":"Im doing great how are you doing?","status":1,"time":1607180786655,"createdAt":"2020-12-05T15:06:26.683Z","updatedAt":"2020-12-28T18:43:34.935Z","__v":0},{"_id":"5fcba2077d1d61c03a6306ae","conversationid":"5fc78bb694632358e5f3891e_tufike_5f628a855c2771d2cf3d7bf6","sender":"5fc78bb694632358e5f3891e","receiver":"5f628a855c2771d2cf3d7bf6","sendername":"Nicole Moraa","receivername":"Felix Oenga","senderphoto":"5fc78bb694632358e5f3891e.png","receiverphoto":"5f628a855c2771d2cf3d7bf6.png","message":"Great, my wife is pregnant dude. I messed","status":1,"time":1607180807764,"createdAt":"2020-12-05T15:06:47.806Z","updatedAt":"2020-12-28T18:43:34.935Z","__v":0},{"_id":"5fcba2157d1d61c03a6306af","conversationid":"5fc78bb694632358e5f3891e_tufike_5f628a855c2771d2cf3d7bf6","sender":"5f628a855c2771d2cf3d7bf6","receiver":"5fc78bb694632358e5f3891e","sendername":"Felix Oenga","receivername":"Nicole Moraa","senderphoto":"5f628a855c2771d2cf3d7bf6.png","receiverphoto":"5fc78bb694632358e5f3891e.png","message":"Oops what happened","status":1,"time":1607180821023,"createdAt":"2020-12-05T15:07:01.039Z","updatedAt":"2020-12-28T18:43:34.935Z","__v":0},{"_id":"5fcba22a7d1d61c03a6306b0","conversationid":"5fc78bb694632358e5f3891e_tufike_5f628a855c2771d2cf3d7bf6","sender":"5fc78bb694632358e5f3891e","receiver":"5f628a855c2771d2cf3d7bf6","sendername":"Nicole Moraa","receivername":"Felix Oenga","senderphoto":"5fc78bb694632358e5f3891e.png","receiverphoto":"5f628a855c2771d2cf3d7bf6.png","message":"I dont know man","status":1,"time":1607180842315,"createdAt":"2020-12-05T15:07:22.370Z","updatedAt":"2020-12-28T18:43:34.935Z","__v":0},{"_id":"5fcba2337d1d61c03a6306b1","conversationid":"5fc78bb694632358e5f3891e_tufike_5f628a855c2771d2cf3d7bf6","sender":"5f628a855c2771d2cf3d7bf6","receiver":"5fc78bb694632358e5f3891e","sendername":"Felix Oenga","receivername":"Nicole Moraa","senderphoto":"5f628a855c2771d2cf3d7bf6.png","receiverphoto":"5fc78bb694632358e5f3891e.png","message":"Well","status":1,"time":1607180851430,"createdAt":"2020-12-05T15:07:31.468Z","updatedAt":"2020-12-28T18:43:34.935Z","__v":0},{"_id":"5fcba2397d1d61c03a6306b2","conversationid":"5fc78bb694632358e5f3891e_tufike_5f628a855c2771d2cf3d7bf6","sender":"5fc78bb694632358e5f3891e","receiver":"5f628a855c2771d2cf3d7bf6","sendername":"Nicole Moraa","receivername":"Felix Oenga","senderphoto":"5fc78bb694632358e5f3891e.png","receiverphoto":"5f628a855c2771d2cf3d7bf6.png","message":"What","status":1,"time":1607180857408,"createdAt":"2020-12-05T15:07:37.445Z","updatedAt":"2020-12-28T18:43:34.935Z","__v":0},{"_id":"5fcba2407d1d61c03a6306b3","conversationid":"5fc78bb694632358e5f3891e_tufike_5f628a855c2771d2cf3d7bf6","sender":"5f628a855c2771d2cf3d7bf6","receiver":"5fc78bb694632358e5f3891e","sendername":"Felix Oenga","receivername":"Nicole Moraa","senderphoto":"5f628a855c2771d2cf3d7bf6.png","receiverphoto":"5fc78bb694632358e5f3891e.png","message":"Nothing","status":1,"time":1607180864154,"createdAt":"2020-12-05T15:07:44.216Z","updatedAt":"2020-12-28T18:43:34.935Z","__v":0},{"_id":"5fcba2477d1d61c03a6306b4","conversationid":"5fc78bb694632358e5f3891e_tufike_5f628a855c2771d2cf3d7bf6","sender":"5fc78bb694632358e5f3891e","receiver":"5f628a855c2771d2cf3d7bf6","sendername":"Nicole Moraa","receivername":"Felix Oenga","senderphoto":"5fc78bb694632358e5f3891e.png","receiverphoto":"5f628a855c2771d2cf3d7bf6.png","message":"Oh great","status":1,"time":1607180871351,"createdAt":"2020-12-05T15:07:51.388Z","updatedAt":"2020-12-28T18:43:34.935Z","__v":0}]